colorant/__init__.py
colorant/colorant.py
colorant-1.0.0.dist-info/LICENSE
colorant-1.0.0.dist-info/METADATA
colorant-1.0.0.dist-info/WHEEL
colorant-1.0.0.dist-info/top_level.txt
colorant-1.0.0.dist-info/RECORD
