Metadata-Version: 2.1
Name: colorant
Version: 1.0.0
Summary: Sets text colors and effects in console
Home-page: https://github.com/Nick-Lrc/colorant
Author: Nick Liu
Author-email: itrust19@yahoo.com
License: UNKNOWN
Platform: UNKNOWN
Classifier: Programming Language :: Python :: 3
Classifier: License :: OSI Approved :: MIT License
Classifier: Operating System :: OS Independent
Requires-Python: >=3.6
License-File: LICENSE
